{
	"animations": [
		{
			"loop": false,
			"offsets": [
				-6,
				0
			],
			"anim": "idle",
			"fps": 24,
			"name": "chud idle",
			"indices": []
		},
		{
			"loop": false,
			"offsets": [
				0,
				0
			],
			"anim": "singLEFT",
			"fps": 24,
			"name": "chud left",
			"indices": []
		},
		{
			"loop": false,
			"offsets": [
				0,
				0
			],
			"anim": "singDOWN",
			"fps": 24,
			"name": "chud down",
			"indices": []
		},
		{
			"loop": false,
			"offsets": [
				0,
				0
			],
			"anim": "singUP",
			"fps": 24,
			"name": "chud up",
			"indices": []
		},
		{
			"loop": false,
			"offsets": [
				0,
				0
			],
			"anim": "singRIGHT",
			"fps": 24,
			"name": "chud right",
			"indices": []
		}
	],
	"no_antialiasing": false,
	"image": "characters/chud",
	"position": [
		0,
		330
	],
	"healthicon": "darnell",
	"flip_x": false,
	"healthbar_colors": [
		95,
		85,
		142
	],
	"camera_position": [
		100,
		100
	],
	"sing_duration": 6.1,
	"scale": 1
}